archivy_pocket/__init__.py
archivy_pocket-0.2.0.dist-info/METADATA
archivy_pocket-0.2.0.dist-info/WHEEL
archivy_pocket-0.2.0.dist-info/entry_points.txt
archivy_pocket-0.2.0.dist-info/top_level.txt
archivy_pocket-0.2.0.dist-info/RECORD
