Metadata-Version: 2.1
Name: archivy-pocket
Version: 0.2.0
Summary: Archivy extension to sync content to your pocket account.
Home-page: UNKNOWN
Author: Uzay-G
Author-email: halcyon@disroot.org
License: UNKNOWN
Platform: UNKNOWN
Classifier: Programming Language :: Python :: 3
Classifier: License :: OSI Approved :: MIT License
Requires-Dist: archivy
Requires-Dist: tinydb
Requires-Dist: click
Requires-Dist: requests
